<keymap version="1" name="macOSmy" parent="Mac OS X 10.5+">
  <action id="AceAction">
    <keyboard-shortcut first-keystroke="ctrl semicolon" />
    <keyboard-shortcut first-keystroke="alt f" />
  </action>
  <action id="CloseAllEditorsButActive">
    <keyboard-shortcut first-keystroke="shift ctrl w" />
  </action>
  <action id="CopyThenJumpPaste" />
  <action id="CopyWithoutSelect" />
  <action id="Generate">
    <keyboard-shortcut first-keystroke="ctrl enter" />
    <keyboard-shortcut first-keystroke="alt n" />
  </action>
  <action id="GotoAction">
    <keyboard-shortcut first-keystroke="shift meta p" />
  </action>
  <action id="GotoFile">
    <keyboard-shortcut first-keystroke="shift meta o" />
    <keyboard-shortcut first-keystroke="meta alt n" />
  </action>
  <action id="HideAllWindows">
    <keyboard-shortcut first-keystroke="shift meta f12" />
    <keyboard-shortcut first-keystroke="alt a" />
  </action>
  <action id="HighlightNextSymbol" />
  <action id="HighlightPrevSymbol" />
  <action id="Inline" />
  <action id="JustOneSpace" />
  <action id="NewElement">
    <keyboard-shortcut first-keystroke="ctrl enter" />
  </action>
  <action id="Vcs.QuickListPopupAction">
    <keyboard-shortcut first-keystroke="ctrl v" />
    <keyboard-shortcut first-keystroke="alt back_quote" />
  </action>
  <action id="emacsIDEAs.AceJump">
    <keyboard-shortcut first-keystroke="alt f" />
  </action>
  <action id="emacsIDEAs.AceJumpAndReplace.Block" />
  <action id="emacsIDEAs.AceJumpAndReplace.Group" />
  <action id="emacsIDEAs.AceJumpAndReplace.Line" />
  <action id="emacsIDEAs.AceJumpAndReplace.Paragraph" />
  <action id="emacsIDEAs.AceJumpAndReplace.Quote" />
  <action id="emacsIDEAs.AceJumpAndReplace.String" />
  <action id="emacsIDEAs.AceJumpAndReplace.ToLineEnd" />
  <action id="emacsIDEAs.AceJumpAndReplace.ToLineStart" />
  <action id="emacsIDEAs.AceJumpAndReplace.ToParagraphEnd" />
  <action id="emacsIDEAs.AceJumpAndReplace.ToParagraphStart" />
  <action id="emacsIDEAs.AceJumpAndReplace.Word" />
  <action id="emacsIDEAs.AceJumpCopy" />
  <action id="emacsIDEAs.AceJumpCopy.Block" />
  <action id="emacsIDEAs.AceJumpCopy.Group" />
  <action id="emacsIDEAs.AceJumpCopy.Line" />
  <action id="emacsIDEAs.AceJumpCopy.Paragraph" />
  <action id="emacsIDEAs.AceJumpCopy.Quote" />
  <action id="emacsIDEAs.AceJumpCopy.String" />
  <action id="emacsIDEAs.AceJumpCopy.ToLineEnd" />
  <action id="emacsIDEAs.AceJumpCopy.ToLineStart" />
  <action id="emacsIDEAs.AceJumpCopy.ToParagraphEnd" />
  <action id="emacsIDEAs.AceJumpCopy.ToParagraphStart" />
  <action id="emacsIDEAs.AceJumpCopy.Word" />
  <action id="emacsIDEAs.AceJumpCut" />
  <action id="emacsIDEAs.AceJumpDelete.Block" />
  <action id="emacsIDEAs.AceJumpDelete.Group" />
  <action id="emacsIDEAs.AceJumpDelete.Line" />
  <action id="emacsIDEAs.AceJumpDelete.Paragraph" />
  <action id="emacsIDEAs.AceJumpDelete.Quote" />
  <action id="emacsIDEAs.AceJumpDelete.String" />
  <action id="emacsIDEAs.AceJumpDelete.ToLineEnd" />
  <action id="emacsIDEAs.AceJumpDelete.ToLineStart" />
  <action id="emacsIDEAs.AceJumpDelete.ToParagraphEnd" />
  <action id="emacsIDEAs.AceJumpDelete.ToParagraphStart" />
  <action id="emacsIDEAs.AceJumpDelete.Word" />
  <action id="emacsIDEAs.AceJumpMove.Block" />
  <action id="emacsIDEAs.AceJumpMove.Group" />
  <action id="emacsIDEAs.AceJumpMove.Line" />
  <action id="emacsIDEAs.AceJumpMove.Paragraph" />
  <action id="emacsIDEAs.AceJumpMove.Quote" />
  <action id="emacsIDEAs.AceJumpMove.String" />
  <action id="emacsIDEAs.AceJumpMove.ToLineEnd" />
  <action id="emacsIDEAs.AceJumpMove.ToLineStart" />
  <action id="emacsIDEAs.AceJumpMove.ToParagraphEnd" />
  <action id="emacsIDEAs.AceJumpMove.ToParagraphStart" />
  <action id="emacsIDEAs.AceJumpMove.Word" />
  <action id="emacsIDEAs.AceJumpObtainThenReplace.Block" />
  <action id="emacsIDEAs.AceJumpObtainThenReplace.Group" />
  <action id="emacsIDEAs.AceJumpObtainThenReplace.Line" />
  <action id="emacsIDEAs.AceJumpObtainThenReplace.Paragraph" />
  <action id="emacsIDEAs.AceJumpObtainThenReplace.Quote" />
  <action id="emacsIDEAs.AceJumpObtainThenReplace.String" />
  <action id="emacsIDEAs.AceJumpObtainThenReplace.ToLineEnd" />
  <action id="emacsIDEAs.AceJumpObtainThenReplace.ToLineStart" />
  <action id="emacsIDEAs.AceJumpObtainThenReplace.ToParagraphEnd" />
  <action id="emacsIDEAs.AceJumpObtainThenReplace.ToParagraphStart" />
  <action id="emacsIDEAs.AceJumpObtainThenReplace.Word" />
  <action id="emacsIDEAs.AceJumpSelect" />
  <action id="emacsIDEAs.AceJumpWord" />
</keymap>